jrpyspark/__init__.py
jrpyspark/__version__.py
jrpyspark/data/abalone.zip
jrpyspark/data/airports.zip
jrpyspark/data/ames_housing.zip
jrpyspark/data/birds.zip
jrpyspark/data/flights.zip
jrpyspark/data/movies.zip
jrpyspark/data/spotify.zip
jrpyspark/data/yeast.zip
jrpyspark/data.py
jrpyspark-0.1.1.dist-info/METADATA
jrpyspark-0.1.1.dist-info/WHEEL
jrpyspark-0.1.1.dist-info/RECORD
