Metadata-Version: 2.1
Name: jrpyspark
Version: 0.1.1
Summary: Jumping Rivers: Big Data Analytics with PySpark
Author: Jumping Rivers
Author-email: info@jumpingrivers.com
Requires-Python: >=3.8
Classifier: Programming Language :: Python :: 3
Classifier: Programming Language :: Python :: 3.8
Classifier: Programming Language :: Python :: 3.9
Classifier: Programming Language :: Python :: 3.10
Classifier: Programming Language :: Python :: 3.11
Requires-Dist: matplotlib (>=3.6.3,<4.0.0)
Requires-Dist: numpy (>=1.24.1,<2.0.0)
Requires-Dist: pandas (>=1.5.3,<2.0.0)
Requires-Dist: pyarrow (>=12.0.1,<13.0.0)
Requires-Dist: pyspark (>=3.4.1,<4.0.0)
